demopythonlib/__init__.py
demopythonlib/cmd.py
demopythonlib/do_something.py
demopythonlib-0.1.5.dist-info/METADATA
demopythonlib-0.1.5.dist-info/WHEEL
demopythonlib-0.1.5.dist-info/entry_points.txt
demopythonlib-0.1.5.dist-info/RECORD
