Metadata-Version: 2.1
Name: demopythonlib
Version: 0.1.5
Summary: 
Author: NhanDD3
Author-email: hp.duongducnhan@gmail.com
Requires-Python: >=3.10.0
Classifier: Programming Language :: Python :: 3
Classifier: Programming Language :: Python :: 3.10
Classifier: Programming Language :: Python :: 3.11
Classifier: Programming Language :: Python :: 3.12
